ragbandit/__init__.py
ragbandit/schema.py
ragbandit/config/__init__.py
ragbandit/config/llms.py
ragbandit/config/pricing.py
ragbandit/documents/__init__.py
ragbandit/documents/document_pipeline.py
ragbandit/documents/chunkers/__init__.py
ragbandit/documents/chunkers/base_chunker.py
ragbandit/documents/chunkers/fixed_size_chunker.py
ragbandit/documents/chunkers/semantic_chunker.py
ragbandit/documents/embedders/__init__.py
ragbandit/documents/embedders/base_embedder.py
ragbandit/documents/embedders/mistral_embedder.py
ragbandit/documents/ocr/__init__.py
ragbandit/documents/ocr/base_ocr.py
ragbandit/documents/ocr/mistral_ocr.py
ragbandit/documents/processors/__init__.py
ragbandit/documents/processors/base_processor.py
ragbandit/documents/processors/footnotes_processor.py
ragbandit/documents/processors/references_processor.py
ragbandit/documents/utils/__init__.py
ragbandit/documents/utils/secure_file_handler.py
ragbandit/prompt_tools/__init__.py
ragbandit/prompt_tools/footnotes_processor_tools.py
ragbandit/prompt_tools/prompt_tool.py
ragbandit/prompt_tools/references_processor_tools.py
ragbandit/prompt_tools/semantic_chunker_tools.py
ragbandit/utils/__init__.py
ragbandit/utils/in_memory_log_handler.py
ragbandit/utils/llm_utils.py
ragbandit/utils/mistral_client.py
ragbandit/utils/token_usage_tracker.py
ragbandit_core-0.1.1.dist-info/licenses/LICENSE.md
ragbandit_core-0.1.1.dist-info/METADATA
ragbandit_core-0.1.1.dist-info/WHEEL
ragbandit_core-0.1.1.dist-info/top_level.txt
ragbandit_core-0.1.1.dist-info/RECORD
