Metadata-Version: 2.4
Name: ragbandit-core
Version: 0.1.1
Summary: Core utilities for document processing, RAG configuration, querying, and evaluation.
Author-email: Martim Chaves <martim@ragbandit.com>
License: MIT
Project-URL: Homepage, https://github.com/MartimChaves/ragbandit-core
Project-URL: Documentation, https://github.com/MartimChaves/ragbandit-core#readme
Project-URL: Source, https://github.com/MartimChaves/ragbandit-core
Project-URL: Issues, https://github.com/MartimChaves/ragbandit-core/issues
Classifier: Programming Language :: Python
Classifier: Programming Language :: Python :: 3
Classifier: License :: OSI Approved :: MIT License
Classifier: Operating System :: OS Independent
Requires-Python: >=3.10
License-File: LICENSE.md
Requires-Dist: pydantic>=2.11.7
Requires-Dist: llama-index>=0.12.52
Requires-Dist: mistralai>=1.7.0
Requires-Dist: ragas>=0.3.0
Requires-Dist: cryptography>=44.0.2
Dynamic: license-file
